revanalyzer/REV_analyzer.py
revanalyzer/REV_formulas.py
revanalyzer/__init__.py
revanalyzer/generators/__init__.py
revanalyzer/generators/fdmss_generator.py
revanalyzer/generators/pnm_generator.py
revanalyzer/generators/utils.py
revanalyzer/jl/__init__.py
revanalyzer/jl/corfunction_xyz.jl
revanalyzer/jl/euler_density.jl
revanalyzer/metrics/__init__.py
revanalyzer/metrics/basic_metric.py
revanalyzer/metrics/cf.py
revanalyzer/metrics/euler_density_i.py
revanalyzer/metrics/pd.py
revanalyzer/metrics/permeability.py
revanalyzer/metrics/pnm.py
revanalyzer/metrics/porosity.py
revanalyzer/vectorizers/__init__.py
revanalyzer/vectorizers/basic_vectorizer.py
revanalyzer/vectorizers/cf_vectorizer.py
revanalyzer/vectorizers/direct_vectorizer.py
revanalyzer/vectorizers/hist_vectorizer.py
revanalyzer/vectorizers/landscape_vectorizer.py
revanalyzer/vectorizers/persistence_image_vectorizer.py
revanalyzer/vectorizers/silhouette_vectorizer.py
revanalyzer/vectorizers/simple_binning_vectorizer.py
revanalyzer-0.2.0.dist-info/METADATA
revanalyzer-0.2.0.dist-info/WHEEL
revanalyzer-0.2.0.dist-info/licenses/LICENSE
revanalyzer-0.2.0.dist-info/RECORD
