Metadata-Version: 2.4
Name: revanalyzer
Version: 0.2.0
Summary: Package for representativity analysis of 3D binary images
Project-URL: Documentation, https://fatimp.github.io/REVAnalyzer/index.html
Project-URL: Repository, https://github.com/fatimp/REVAnalyzer
Project-URL: Changelog, https://github.com/fatimp/REVAnalyzer/blob/main/CHANGELOG.md
Author-email: Andrey Zubov <zubov.an.se@gmail.com>
License-Expression: MIT
License-File: LICENSE
Keywords: 3D images,REV,image analysis
Classifier: Programming Language :: Python
Requires-Python: >=3.9
Requires-Dist: gudhi
Requires-Dist: matplotlib
Requires-Dist: numpy
Requires-Dist: openpnm
Requires-Dist: pandas
Requires-Dist: porespy
Requires-Dist: pyfdmss
Requires-Dist: pyperspairdiamorse
Requires-Dist: scikit-learn
